{
  "TrainerName": "Stubs",
  "teamInfo": {
    "SavedSlime": [
      {
        "PartNames": [
          "Spider Web",
          "SlimeBodyBase",
          "Torment",
          "Megahorn",
          "Switcheroo",
          "Steamroller",
          "Dragon Snot"
        ],
        "SlimeName": "",
        "secret": "369ef834-171e-40c9-a427-2e84947df75a",
        "TeamPos": 2,
        "myCardType": [
          76,
          5,
          86,
          52,
          82,
          77,
          30
        ]
      }
    ]
  }
}